setup.cfg
setup.py
django_helper_builder/__init__.py
django_helper_builder/main.py
django_helper_builder.egg-info/PKG-INFO
django_helper_builder.egg-info/SOURCES.txt
django_helper_builder.egg-info/dependency_links.txt
django_helper_builder.egg-info/not-zip-safe
django_helper_builder.egg-info/top_level.txt